{
    "activation": {
        "Subject": "Vítejte! Ověřte prosím svou e-mailovou adresu.",
        "Thanks": "Vítejte v {{1}}",
        "ReallyYourEmail": "Je to opravdu vaše e-mailová adresa, {{1}}? Pokud ano, klikněte <a href='{{2}}'>sem<\/a> a nastavte si přístupové heslo a aktivujte svůj účet.",
        "SeeYou": "Uvidíme se na <a href='{{1}}'>{{2}}<\/a> !"
    },
    "identifier": {
        "Subject": "Vítejte! Ověřte svou e-mailovou adresu."
    },
    "resend": {
        "Subject": "Hej, zapomněl jsi heslo?",
        "Thanks": "Děkujeme za návštěvu {{1}}",
        "YouAreReceiving": "Tento e-mail jste obdrželi, protože někdo zadal vaši e-mailovou adresu a klikl na „zapomněl jsem heslo“. Pokud jste to nebyli vy, jednoduše tuto zprávu ignorujte.",
        "Reset": "Chcete-li resetovat přístupovou frázi, klikněte na {{1}}",
        "SetUpPassphrase": "Nastavte přístupovou frázi",
        "DomainCode": "Pokud je webová stránka již otevřena ve vašem prohlížeči, můžete zadat kód <strong>{{code}}<\/strong>"
    },
    "SeeYou": "Uvidíme se na {{1}}!",
    "LinkToUnsubscribe": "Zde je odkaz pro <a href='{{1}}'>odhlášení<\/a> , pokud již nechcete dostávat žádné další e-maily.",
    "Greetings": "Zdravím vás z {{1}}.",
    "SeeHistory": "Zobrazit historii plateb za {{1}}",
    "charge": {
        "HasBeenCharged": "Dobrý den, tímto vám chceme oznámit, že {{4}} byla účtována částka {{1}} {{2}} za {{3}}"
    },
    "charged": {
        "HavePaid": "Dobrý den, {{1}}, toto je jen rychlé potvrzení, že jste úspěšně zaplatili {{2}} uživateli {{3}} za {{4}}"
    },
    "subscription": {
        "YouHaveStarted": "Dobrý den, {{1}}, zahájili jste své předplatné {{2}} s {{3}} v {{4}} na {{5}} měsíce.",
        "HasStarted": "Tímto vám chceme oznámit, že {{1}} zahájil své předplatné {{2}} s {{3}} v {{4}} na {{5}} měsíců."
    }
}